plotvec/__init__.py
plotvec/plotvec.py
plotvec/transforms.py
plotvec-1.7.3.dist-info/LICENSE
plotvec-1.7.3.dist-info/WHEEL
plotvec-1.7.3.dist-info/METADATA
plotvec-1.7.3.dist-info/RECORD
