Metadata-Version: 2.1
Name: plotvec
Version: 1.7.3
Summary: Module to plot 2-d vectors as arrows using Matplotlib.  
Home-page: https://github.com/jmshea/plotvec
Author: John M. Shea
Author-email: jshea@ieee.org
Classifier: License :: OSI Approved :: MIT License
